ngsci/__init__.py
ngsci/calculator.py
ngsci/parser.py
ngsci-0.0.1.data/scripts/ngsci
test/__init__.py
test/test_calculator.py
test/test_parser.py
ngsci-0.0.1.dist-info/LICENSE
ngsci-0.0.1.dist-info/METADATA
ngsci-0.0.1.dist-info/WHEEL
ngsci-0.0.1.dist-info/top_level.txt
ngsci-0.0.1.dist-info/RECORD
